phenopacket/__init__.py
phenopacket/cnv_phenopacket.py
cnv_phenopacket-1.0.2.dist-info/METADATA
cnv_phenopacket-1.0.2.dist-info/WHEEL
cnv_phenopacket-1.0.2.dist-info/entry_points.txt
cnv_phenopacket-1.0.2.dist-info/top_level.txt
cnv_phenopacket-1.0.2.dist-info/RECORD
