Metadata-Version: 2.1
Name: cnv-phenopacket
Version: 1.0.2
Summary: Convert TSV metadata to Phenopacket JSON
Author: Khaled Jumah
Author-email: khalled.joomah@yahoo.com
Requires-Dist: jsonschema
